llm_arxiv.py
llm_arxiv-0.1.2.dist-info/licenses/LICENSE
llm_arxiv-0.1.2.dist-info/METADATA
llm_arxiv-0.1.2.dist-info/WHEEL
llm_arxiv-0.1.2.dist-info/entry_points.txt
llm_arxiv-0.1.2.dist-info/top_level.txt
llm_arxiv-0.1.2.dist-info/RECORD
