Metadata-Version: 2.4
Name: llm-arxiv
Version: 0.1.2
Summary: LLM plugin for loading arXiv papers
Author: Agusti F.
License: Apache-2.0
Project-URL: Homepage, https://github.com/agustif/llm-arxiv
Project-URL: Changelog, https://github.com/agustif/llm-arxiv/releases
Project-URL: Issues, https://github.com/agustif/llm-arxiv/issues
Project-URL: CI, https://github.com/agustif/llm-arxiv/actions
Classifier: License :: OSI Approved :: Apache Software License
License-File: LICENSE
Requires-Dist: llm
Requires-Dist: arxiv
Requires-Dist: PyMuPDF
Provides-Extra: test
Requires-Dist: pytest; extra == "test"
Dynamic: license-file
